smartsurge/__init__.py
smartsurge/client.py
smartsurge/exceptions.py
smartsurge/hmm.py
smartsurge/logging_.py
smartsurge/models.py
smartsurge/streaming.py
smartsurge/utilities.py
smartsurge/benchmarks/BENCHMARKS.md
smartsurge/benchmarks/README.md
smartsurge/benchmarks/baseline_client.py
smartsurge/benchmarks/benchmark_hmm_effectiveness.py
smartsurge/benchmarks/benchmark_hmm_performance.py
smartsurge/benchmarks/mock_server.py
smartsurge/benchmarks/run_benchmark_suite.py
smartsurge/benchmarks/run_hmm_benchmark.sh
smartsurge/benchmarks/visualize_results.py
smartsurge/docs/advanced_usage.md
smartsurge/docs/basic_usage.md
smartsurge/docs/benchmark_usage.md
smartsurge/docs/examples.md
smartsurge/docs/getting_started.md
smartsurge/docs/index.md
smartsurge/docs/api/client.md
smartsurge/docs/api/exceptions.md
smartsurge/docs/api/hmm.md
smartsurge/docs/api/index.md
smartsurge/docs/api/models.md
smartsurge/docs/api/streaming.md
smartsurge-0.0.7.dist-info/licenses/LICENSE
smartsurge-0.0.7.dist-info/METADATA
smartsurge-0.0.7.dist-info/WHEEL
smartsurge-0.0.7.dist-info/entry_points.txt
smartsurge-0.0.7.dist-info/top_level.txt
smartsurge-0.0.7.dist-info/RECORD
