Metadata-Version: 2.4
Name: smartsurge
Version: 0.0.7
Summary: Enhanced Requests Library with Adaptive Rate Limit Estimation
Author-email: Ryan Taylor <ryan@beta-reduce.net>
License-Expression: Apache-2.0
Project-URL: Homepage, https://github.com/dingo-actual/smartsurge
Project-URL: Documentation, https://github.com/dingo-actual/smartsurge/docs/index.md
Project-URL: Repository, https://github.com/dingo-actual/smartsurge
Project-URL: Issues, https://github.com/dingo-actual/smartsurge/issues
Keywords: http,requests,rate-limit,api,hmm,adaptive
Classifier: Development Status :: 3 - Alpha
Classifier: Intended Audience :: Developers
Classifier: Programming Language :: Python :: 3
Classifier: Programming Language :: Python :: 3.9
Classifier: Programming Language :: Python :: 3.10
Classifier: Programming Language :: Python :: 3.11
Classifier: Programming Language :: Python :: 3.12
Classifier: Programming Language :: Python :: 3.13
Requires-Python: >=3.9
License-File: LICENSE
Requires-Dist: requests>=2.0.0
Requires-Dist: aiohttp>=3.0.0
Requires-Dist: pydantic>=2.0.0
Requires-Dist: scipy>=1.0.0
Provides-Extra: dev
Requires-Dist: pytest>=8.0.0; extra == "dev"
Requires-Dist: pytest-asyncio>=0.25.0; extra == "dev"
Requires-Dist: pytest-cov>=5.0.0; extra == "dev"
Requires-Dist: black>=25.0.0; extra == "dev"
Requires-Dist: isort>=6.0.0; extra == "dev"
Requires-Dist: mypy>=1.0.0; extra == "dev"
Requires-Dist: flake8>=7.0.0; extra == "dev"
Requires-Dist: werkzeug>=3.0.0; extra == "dev"
Requires-Dist: flask>=3.0.0; extra == "dev"
Requires-Dist: numpy>=2.0.0; extra == "dev"
Requires-Dist: pyperf>=2.0.0; extra == "dev"
Provides-Extra: docs
Requires-Dist: mkdocs>=1.0.0; extra == "docs"
Requires-Dist: mkdocs-material>=9.0.0; extra == "docs"
Requires-Dist: mkdocstrings[python]>=0.28.0; extra == "docs"
Requires-Dist: setuptools>=42; extra == "docs"
Requires-Dist: wheel; extra == "docs"
Provides-Extra: benchmark
Requires-Dist: pyperf>=2.0.0; extra == "benchmark"
Requires-Dist: matplotlib>=3.0.0; extra == "benchmark"
Requires-Dist: numpy>=2.0.0; extra == "benchmark"
Requires-Dist: flask>=3.0.0; extra == "benchmark"
Requires-Dist: werkzeug>=3.0.0; extra == "benchmark"
Dynamic: license-file
